smart_cv/VectorDB.py
smart_cv/__init__.py
smart_cv/base.py
smart_cv/interface.py
smart_cv/resume_parser.py
smart_cv/st_interface.py
smart_cv/util.py
smart_cv-0.0.3.dist-info/METADATA
smart_cv-0.0.3.dist-info/WHEEL
smart_cv-0.0.3.dist-info/top_level.txt
smart_cv-0.0.3.dist-info/RECORD
